hypersync-0.8.5.dist-info/METADATA
hypersync-0.8.5.dist-info/WHEEL
hypersync-0.8.5.dist-info/licenses/LICENSE
hypersync/__init__.py
hypersync/hypersync.cp39-win_amd64.pyd
hypersync-0.8.5.dist-info/RECORD
