Metadata-Version: 2.4
Name: hypersync
Version: 0.8.5
Classifier: Programming Language :: Rust
Classifier: Programming Language :: Python :: Implementation :: CPython
Classifier: Programming Language :: Python :: Implementation :: PyPy
Classifier: Development Status :: 3 - Alpha
Classifier: Topic :: Database :: Front-Ends
Classifier: Topic :: Software Development :: Libraries
Requires-Dist: strenum >=0.4.15, <0.4.16
License-File: LICENSE
Requires-Python: >=3.9
Project-URL: homepage, https://envio.dev/
Project-URL: documentation, https://docs.envio.dev/docs/HyperSync/overview
Project-URL: repository, https://github.com/enviodev/hypersync-client-python
